countdown/__init__.py
countdown-0.1.0.dist-info/WHEEL
countdown-0.1.0.dist-info/METADATA
countdown-0.1.0.dist-info/RECORD
