Metadata-Version: 2.1
Name: countdown
Version: 0.1.0
Summary: Package to solve the number round from the Channel 4 television show "Countdown"
License: MIT
Author: Valentin Calomme
Author-email: info@valentincalomme.com
Requires-Python: >=3.7,<4.0
Classifier: License :: OSI Approved :: MIT License
Classifier: Programming Language :: Python :: 3
Classifier: Programming Language :: Python :: 3.7
Classifier: Programming Language :: Python :: 3.8
